CHANGES.txt
LICENSE.txt
MANIFEST.in
README.txt
TODO.txt
bootstrap.py
buildout.cfg
setup.py
eggs/ZConfig-4.2-py3.10.egg/EGG-INFO/LICENSE.txt
eggs/ZConfig-4.2-py3.10.egg/EGG-INFO/entry_points.txt
eggs/ZConfig-4.2-py3.10.egg/EGG-INFO/requires.txt
eggs/ZConfig-4.2-py3.10.egg/EGG-INFO/top_level.txt
eggs/ZConfig-4.2-py3.10.egg/ZConfig/schemaless.txt
eggs/ZConfig-4.2-py3.10.egg/ZConfig/tests/input/non-ascii.txt
eggs/ZConfig-4.2-py3.10.egg/ZConfig/tests/library/README.txt
eggs/ZConfig-4.2-py3.10.egg/ZConfig/tests/zipsource/README.txt
eggs/argparse-1.4.0-py3.10.egg/EGG-INFO/top_level.txt
eggs/coverage-7.10.3-py3.10.egg/EGG-INFO/entry_points.txt
eggs/coverage-7.10.3-py3.10.egg/EGG-INFO/requires.txt
eggs/coverage-7.10.3-py3.10.egg/EGG-INFO/top_level.txt
eggs/coverage-7.10.3-py3.10.egg/EGG-INFO/licenses/LICENSE.txt
eggs/coverage-7.9.2-py3.10-win-amd64.egg/EGG-INFO/entry_points.txt
eggs/coverage-7.9.2-py3.10-win-amd64.egg/EGG-INFO/requires.txt
eggs/coverage-7.9.2-py3.10-win-amd64.egg/EGG-INFO/top_level.txt
eggs/coverage-7.9.2-py3.10-win-amd64.egg/EGG-INFO/licenses/LICENSE.txt
eggs/cssmin-0.2.0-py3.10.egg/EGG-INFO/SOURCES.txt
eggs/cssmin-0.2.0-py3.10.egg/EGG-INFO/dependency_links.txt
eggs/cssmin-0.2.0-py3.10.egg/EGG-INFO/entry_points.txt
eggs/cssmin-0.2.0-py3.10.egg/EGG-INFO/top_level.txt
eggs/future-1.0.0-py3.10.egg/EGG-INFO/LICENSE.txt
eggs/future-1.0.0-py3.10.egg/EGG-INFO/entry_points.txt
eggs/future-1.0.0-py3.10.egg/EGG-INFO/top_level.txt
eggs/jsmin-3.0.1-py3.10.egg/EGG-INFO/SOURCES.txt
eggs/jsmin-3.0.1-py3.10.egg/EGG-INFO/dependency_links.txt
eggs/jsmin-3.0.1-py3.10.egg/EGG-INFO/top_level.txt
eggs/lovely.recipe-1.0.0-py3.10.egg/EGG-INFO/SOURCES.txt
eggs/lovely.recipe-1.0.0-py3.10.egg/EGG-INFO/dependency_links.txt
eggs/lovely.recipe-1.0.0-py3.10.egg/EGG-INFO/entry_points.txt
eggs/lovely.recipe-1.0.0-py3.10.egg/EGG-INFO/namespace_packages.txt
eggs/lovely.recipe-1.0.0-py3.10.egg/EGG-INFO/requires.txt
eggs/lovely.recipe-1.0.0-py3.10.egg/EGG-INFO/top_level.txt
eggs/lovely.recipe-1.0.0-py3.10.egg/lovely/recipe/egg/README.txt
eggs/lovely.recipe-1.0.0-py3.10.egg/lovely/recipe/fs/README.txt
eggs/lovely.recipe-1.0.0-py3.10.egg/lovely/recipe/fs/mkdir-root.txt
eggs/lovely.recipe-1.0.0-py3.10.egg/lovely/recipe/i18n/README.txt
eggs/lovely.recipe-1.0.0-py3.10.egg/lovely/recipe/importchecker/README.txt
eggs/lpjsmin-0.7-py3.10.egg/EGG-INFO/entry_points.txt
eggs/lpjsmin-0.7-py3.10.egg/EGG-INFO/requires.txt
eggs/lpjsmin-0.7-py3.10.egg/EGG-INFO/top_level.txt
eggs/lxml-6.0.0-py3.10-win-amd64.egg/EGG-INFO/requires.txt
eggs/lxml-6.0.0-py3.10-win-amd64.egg/EGG-INFO/top_level.txt
eggs/lxml-6.0.0-py3.10-win-amd64.egg/EGG-INFO/licenses/LICENSE.txt
eggs/lxml-6.0.0-py3.10-win-amd64.egg/EGG-INFO/licenses/LICENSES.txt
eggs/lxml-6.0.0-py3.10-win-amd64.egg/lxml/isoschematron/resources/xsl/iso-schematron-xslt1/readme.txt
eggs/p01.checker-0.5.12-py3.10.egg/EGG-INFO/SOURCES.txt
eggs/p01.checker-0.5.12-py3.10.egg/EGG-INFO/dependency_links.txt
eggs/p01.checker-0.5.12-py3.10.egg/EGG-INFO/namespace_packages.txt
eggs/p01.checker-0.5.12-py3.10.egg/EGG-INFO/requires.txt
eggs/p01.checker-0.5.12-py3.10.egg/EGG-INFO/top_level.txt
eggs/p01.checker-0.5.12-py3.10.egg/p01/checker/checker.txt
eggs/p01.checker-0.5.12-py3.10.egg/p01/checker/sample/tab.txt
eggs/p01.checker-0.5.9-py3.10.egg/EGG-INFO/SOURCES.txt
eggs/p01.checker-0.5.9-py3.10.egg/EGG-INFO/dependency_links.txt
eggs/p01.checker-0.5.9-py3.10.egg/EGG-INFO/namespace_packages.txt
eggs/p01.checker-0.5.9-py3.10.egg/EGG-INFO/requires.txt
eggs/p01.checker-0.5.9-py3.10.egg/EGG-INFO/top_level.txt
eggs/p01.checker-0.5.9-py3.10.egg/p01/checker/checker.txt
eggs/p01.checker-0.5.9-py3.10.egg/p01/checker/sample/tab.txt
eggs/p01.recipe.setup-0.8.18-py3.10.egg/EGG-INFO/SOURCES.txt
eggs/p01.recipe.setup-0.8.18-py3.10.egg/EGG-INFO/dependency_links.txt
eggs/p01.recipe.setup-0.8.18-py3.10.egg/EGG-INFO/entry_points.txt
eggs/p01.recipe.setup-0.8.18-py3.10.egg/EGG-INFO/namespace_packages.txt
eggs/p01.recipe.setup-0.8.18-py3.10.egg/EGG-INFO/requires.txt
eggs/p01.recipe.setup-0.8.18-py3.10.egg/EGG-INFO/top_level.txt
eggs/p01.recipe.setup-0.8.18-py3.10.egg/p01/recipe/setup/README.txt
eggs/p01.recipe.setup-0.8.18-py3.10.egg/p01/recipe/setup/checker.txt
eggs/p01.recipe.setup-0.8.18-py3.10.egg/p01/recipe/setup/cmd.txt
eggs/p01.recipe.setup-0.8.18-py3.10.egg/p01/recipe/setup/copy.txt
eggs/p01.recipe.setup-0.8.18-py3.10.egg/p01/recipe/setup/download.txt
eggs/p01.recipe.setup-0.8.18-py3.10.egg/p01/recipe/setup/fetch.txt
eggs/p01.recipe.setup-0.8.18-py3.10.egg/p01/recipe/setup/i18n.txt
eggs/p01.recipe.setup-0.8.18-py3.10.egg/p01/recipe/setup/importchecker.txt
eggs/p01.recipe.setup-0.8.18-py3.10.egg/p01/recipe/setup/index.txt
eggs/p01.recipe.setup-0.8.18-py3.10.egg/p01/recipe/setup/mkdir.txt
eggs/p01.recipe.setup-0.8.18-py3.10.egg/p01/recipe/setup/mkfile.txt
eggs/p01.recipe.setup-0.8.18-py3.10.egg/p01/recipe/setup/paste.txt
eggs/p01.recipe.setup-0.8.18-py3.10.egg/p01/recipe/setup/script.txt
eggs/p01.recipe.setup-0.8.18-py3.10.egg/p01/recipe/setup/scripts.txt
eggs/p01.recipe.setup-0.8.19-py3.10.egg/EGG-INFO/SOURCES.txt
eggs/p01.recipe.setup-0.8.19-py3.10.egg/EGG-INFO/dependency_links.txt
eggs/p01.recipe.setup-0.8.19-py3.10.egg/EGG-INFO/entry_points.txt
eggs/p01.recipe.setup-0.8.19-py3.10.egg/EGG-INFO/namespace_packages.txt
eggs/p01.recipe.setup-0.8.19-py3.10.egg/EGG-INFO/requires.txt
eggs/p01.recipe.setup-0.8.19-py3.10.egg/EGG-INFO/top_level.txt
eggs/pillow-11.3.0-py3.10-win-amd64.egg/EGG-INFO/requires.txt
eggs/pillow-11.3.0-py3.10-win-amd64.egg/EGG-INFO/top_level.txt
eggs/ply-3.11-py3.10.egg/EGG-INFO/top_level.txt
eggs/polib-1.2.0-py3.10.egg/EGG-INFO/top_level.txt
eggs/pyflakes-3.4.0-py3.10.egg/EGG-INFO/entry_points.txt
eggs/pyflakes-3.4.0-py3.10.egg/EGG-INFO/top_level.txt
eggs/six-1.17.0-py3.10.egg/EGG-INFO/top_level.txt
eggs/slimit-0.8.1-py3.10.egg/EGG-INFO/SOURCES.txt
eggs/slimit-0.8.1-py3.10.egg/EGG-INFO/dependency_links.txt
eggs/slimit-0.8.1-py3.10.egg/EGG-INFO/entry_points.txt
